{"name": "Burmy", "id": "412", "imageUrl": "https://assets.pokemon.com/assets/cms2/img/pokedex/full/412.png", "types": ["Bug"], "info": {"description": "", "species": "Bagworm Pok\u00e9mon", "height": "0.2m", "weight": "3.4kg", "catchRate": "120", "baseExp": "45", "growthRate": "Medium Fast", "eggGroups": ["Bug"]}, "evolutions": ["Burmy", "Mothim", "Burmy", "Wormadam", "Burmy", "Wormadam", "Burmy", "Wormadam"], "moves": {"levelUp": ["Protect", "Tackle", "Bug Bite", "String Shot", "Struggle Bug"], "egg": [], "tutor": [], "tm": ["Protect"], "tr": []}, "stats": {"hp": {"name": "HP", "base": 40, "min": 190, "max": 284}, "attack": {"name": "Attack", "base": 29, "min": 56, "max": 172}, "defense": {"name": "Defense", "base": 45, "min": 85, "max": 207}, "spAttack": {"name": "Sp. Attack", "base": 45, "min": 85, "max": 207}, "spDefense": {"name": "Sp. Defense", "base": 45, "min": 85, "max": 207}, "speed": {"name": "Speed", "base": 40, "min": 190, "max": 284}}}