{"name": "Cinccino", "id": "573", "imageUrl": "https://assets.pokemon.com/assets/cms2/img/pokedex/full/573.png", "types": ["Normal"], "info": {"description": "", "species": "Scarf Pok\u00e9mon", "height": "0.5m", "weight": "7.5kg", "catchRate": "60", "baseExp": "165", "growthRate": "Fast", "eggGroups": ["Field"]}, "evolutions": ["Minccino", "Cinccino"], "moves": {"levelUp": ["After You", "Baby-Doll Eyes", "Bullet Seed", "Charm", "Echoed Voice", "Encore", "Helping Hand", "Hyper Voice", "Last Resort", "Pound", "Rock Blast", "Sing", "Slam", "Swift", "Tail Slap", "Tickle"], "egg": ["Aqua Tail", "Flail", "Knock Off", "Tail Whip", "Triple Axel", "Endure", "Fake Tears", "Iron Tail", "Mud-Slap", "Sleep Talk", "After You", "Covet", "Gunk Shot", "Helping Hand", "Hyper Voice", "Laser Focus", "Last Resort", "Seed Bomb", "Shock Wave", "Snore", "Uproar", "Baby-Doll Eyes", "Captivate", "Charm", "Double Slap", "Echoed Voice", "Encore", "Pound", "Slam", "Swift", "Wake-Up Slap", "Growl", "Dig", "Retaliate", "Secret Power"], "tutor": ["Triple Axel", "After You", "Aqua Tail", "Covet", "Gunk Shot", "Helping Hand", "Hyper Voice", "Iron Tail", "Knock Off", "Laser Focus", "Last Resort", "Seed Bomb", "Shock Wave", "Snore", "Uproar"], "tm": ["Hyper Beam", "Giga Impact", "Thunder Wave", "Dig", "Light Screen", "Safeguard", "Rest", "Thief", "Snore", "Protect", "Charm", "Attract", "Rain Dance", "Sunny Day", "Facade", "Swift", "Helping Hand", "Fake Tears", "Bullet Seed", "Rock Blast", "U-turn", "Fling", "Round", "Retaliate", "Tail Slap", "Work Up", "Calm Mind", "Toxic", "Hidden Power", "Frustration", "Thunderbolt", "Thunder", "Return", "Double Team", "Echoed Voice", "Focus Blast", "Grass Knot", "Swagger", "Sleep Talk", "Substitute", "Dazzling Gleam", "Confide"], "tr": ["Thunderbolt", "Thunder", "Substitute", "Endure", "Sleep Talk", "Encore", "Iron Tail", "Uproar", "Hyper Voice", "Calm Mind", "Seed Bomb", "Focus Blast", "Gunk Shot", "Grass Knot", "Work Up", "Play Rough", "Dazzling Gleam"]}, "stats": {"hp": {"name": "HP", "base": 75, "min": 260, "max": 354}, "attack": {"name": "Attack", "base": 95, "min": 175, "max": 317}, "defense": {"name": "Defense", "base": 60, "min": 112, "max": 240}, "spAttack": {"name": "Sp. Attack", "base": 60, "min": 112, "max": 240}, "spDefense": {"name": "Sp. Defense", "base": 60, "min": 112, "max": 240}, "speed": {"name": "Speed", "base": 75, "min": 260, "max": 354}}}