{"name": "Gumshoos", "id": "735", "imageUrl": "https://assets.pokemon.com/assets/cms2/img/pokedex/full/735.png", "types": ["Normal"], "info": {"description": "", "species": "Stakeout Pok\u00e9mon", "height": "0.7m", "weight": "14.2kg", "catchRate": "127", "baseExp": "146", "growthRate": "Medium Fast", "eggGroups": ["Field"]}, "evolutions": ["Yungoos", "Gumshoos"], "moves": {"levelUp": ["Leer", "Pursuit", "Sand Attack", "Tackle", "Odor Sleuth", "Bide", "Bite", "Mud-Slap", "Super Fang", "Take Down", "Scary Face", "Crunch", "Hyper Fang", "Yawn", "Thrash", "Rest"], "egg": ["Fire Fang", "Ice Fang", "Last Resort", "Revenge", "Thunder Fang", "Block", "Dual Chop", "Endeavor", "Fire Punch", "Ice Punch", "Iron Head", "Iron Tail", "Shock Wave", "Snore", "Stomping Tantrum", "Super Fang", "Thunder Punch", "Uproar", "Zen Headbutt"], "tutor": ["Block", "Dual Chop", "Endeavor", "Fire Punch", "Ice Punch", "Iron Head", "Iron Tail", "Last Resort", "Shock Wave", "Snore", "Stomping Tantrum", "Super Fang", "Thunder Punch", "Uproar", "Zen Headbutt"], "tm": ["Work Up", "Roar", "Toxic", "Hidden Power", "Taunt", "Protect", "Frustration", "Earthquake", "Return", "Double Team", "Sandstorm", "Rock Tomb", "Torment", "Facade", "Rest", "Attract", "Thief", "Round", "Echoed Voice", "Fling", "Payback", "Bulldoze", "Swagger", "Sleep Talk", "U-turn", "Substitute", "Confide"], "tr": []}, "stats": {"hp": {"name": "HP", "base": 88, "min": 286, "max": 380}, "attack": {"name": "Attack", "base": 110, "min": 202, "max": 350}, "defense": {"name": "Defense", "base": 60, "min": 112, "max": 240}, "spAttack": {"name": "Sp. Attack", "base": 60, "min": 112, "max": 240}, "spDefense": {"name": "Sp. Defense", "base": 60, "min": 112, "max": 240}, "speed": {"name": "Speed", "base": 88, "min": 286, "max": 380}}}