{"name": "Hatterene", "id": "858", "imageUrl": "https://assets.pokemon.com/assets/cms2/img/pokedex/full/858.png", "types": ["Psychic", "Fairy"], "info": {"description": "", "species": "Silent Pok\u00e9mon", "height": "2.1m", "weight": "5.0kg", "catchRate": "45", "baseExp": "255", "growthRate": "Slow", "eggGroups": ["Fairy"]}, "evolutions": ["Hatenna", "Hattrem", "Hatterene"], "moves": {"levelUp": ["Brutal Swing", "Confusion", "Disarming Voice", "Life Dew", "Play Nice", "Psycho Cut", "Aromatherapy", "Psybeam", "Heal Pulse", "Dazzling Gleam", "Calm Mind", "Psychic", "Healing Wish", "Magic Powder"], "egg": ["Psycho Cut", "After You", "Aromatic Mist", "Nuzzle", "Quash", "Expanding Force", "Misty Explosion"], "tutor": ["After You", "Aromatic Mist", "Nuzzle", "Quash"], "tm": ["Hyper Beam", "Giga Impact", "Magical Leaf", "Thunder Wave", "Light Screen", "Safeguard", "Rest", "Snore", "Protect", "Giga Drain", "Charm", "Attract", "Facade", "Helping Hand", "Imprison", "Power Swap", "Guard Swap", "Shadow Claw", "Psycho Cut", "Trick Room", "Wonder Room", "Magic Room", "Round", "Draining Kiss", "Mystical Fire", "Brutal Swing"], "tr": ["Swords Dance", "Psychic", "Substitute", "Psyshock", "Endure", "Sleep Talk", "Baton Pass", "Shadow Ball", "Future Sight", "Skill Swap", "Calm Mind", "Dark Pulse", "Power Whip", "Stored Power", "Play Rough", "Dazzling Gleam"]}, "stats": {"hp": {"name": "HP", "base": 57, "min": 224, "max": 318}, "attack": {"name": "Attack", "base": 90, "min": 166, "max": 306}, "defense": {"name": "Defense", "base": 95, "min": 175, "max": 317}, "spAttack": {"name": "Sp. Attack", "base": 95, "min": 175, "max": 317}, "spDefense": {"name": "Sp. Defense", "base": 95, "min": 175, "max": 317}, "speed": {"name": "Speed", "base": 57, "min": 224, "max": 318}}}