{"name": "Larvesta", "id": "636", "imageUrl": "https://assets.pokemon.com/assets/cms2/img/pokedex/full/636.png", "types": ["Bug", "Fire"], "info": {"description": "", "species": "Torch Pok\u00e9mon", "height": "1.1m", "weight": "28.8kg", "catchRate": "45", "baseExp": "72", "growthRate": "Slow", "eggGroups": ["Bug"]}, "evolutions": ["Larvesta", "Volcarona"], "moves": {"levelUp": ["Ember", "String Shot", "Flame Charge", "Struggle Bug", "Flame Wheel", "Bug Bite", "Screech", "Leech Life", "Bug Buzz", "Take Down", "Amnesia", "Double-Edge", "Flare Blitz", "Absorb", "Thrash"], "egg": ["Absorb", "Harden", "Thrash", "Skitter Smack", "Endure", "Foresight", "Magnet Rise", "Morning Sun", "String Shot", "Zen Headbutt", "Bug Bite", "Giga Drain", "Heat Wave", "Signal Beam", "Snore", "Incinerate", "Secret Power", "Struggle Bug"], "tutor": ["Skitter Smack", "Bug Bite", "Giga Drain", "Heat Wave", "Magnet Rise", "Signal Beam", "Snore", "Zen Headbutt"], "tm": ["Solar Beam", "Screech", "Light Screen", "Safeguard", "Rest", "Snore", "Protect", "Giga Drain", "Attract", "Sunny Day", "Will-O-Wisp", "Facade", "U-turn", "Round", "Acrobatics", "Calm Mind", "Toxic", "Hidden Power", "Frustration", "Return", "Leech Life", "Psychic", "Double Team", "Flamethrower", "Fire Blast", "Flame Charge", "Overheat", "Swagger", "Sleep Talk", "Substitute", "Wild Charge", "Confide"], "tr": ["Flamethrower", "Psychic", "Fire Blast", "Amnesia", "Leech Life", "Substitute", "Endure", "Sleep Talk", "Heat Wave", "Overheat", "Calm Mind", "Flare Blitz", "Bug Buzz", "Zen Headbutt", "Wild Charge"]}, "stats": {"hp": {"name": "HP", "base": 55, "min": 220, "max": 314}, "attack": {"name": "Attack", "base": 85, "min": 157, "max": 295}, "defense": {"name": "Defense", "base": 55, "min": 103, "max": 229}, "spAttack": {"name": "Sp. Attack", "base": 55, "min": 103, "max": 229}, "spDefense": {"name": "Sp. Defense", "base": 55, "min": 103, "max": 229}, "speed": {"name": "Speed", "base": 55, "min": 220, "max": 314}}}