{"name": "Skorupi", "id": "451", "imageUrl": "https://assets.pokemon.com/assets/cms2/img/pokedex/full/451.png", "types": ["Bug", "Poison"], "info": {"description": "", "species": "Scorpion Pok\u00e9mon", "height": "0.8m", "weight": "12.0kg", "catchRate": "120", "baseExp": "66", "growthRate": "Slow", "eggGroups": ["Bug", "Water 3"]}, "evolutions": ["Skorupi", "Drapion"], "moves": {"levelUp": ["Leer", "Poison Sting", "Hone Claws", "Fell Stinger", "Poison Fang", "Bite", "Toxic Spikes", "Bug Bite", "Venoshock", "Knock Off", "Scary Face", "Pin Missile", "Toxic", "Night Slash", "Cross Poison", "X-Scissor", "Acupressure", "Crunch", "Swords Dance"], "egg": ["Agility", "Confuse Ray", "Night Slash", "Poison Tail", "Sand Attack", "Screech", "Slash", "Whirlwind", "Aerial Ace", "Aqua Tail", "Dark Pulse", "False Swipe", "Iron Tail", "Poison Jab", "Rest", "Rock Smash", "Shadow Ball", "Sludge Bomb", "X-Scissor"], "tutor": [], "tm": ["Toxic", "Sunny Day", "Taunt", "Protect", "Rain Dance", "Iron Tail", "Dig", "Shadow Ball", "Brick Break", "Double Team", "Sludge Bomb", "Rock Tomb", "Aerial Ace", "Torment", "Facade", "Rest", "Attract", "Thief", "False Swipe", "Fling", "Endure", "Bug Buzz", "Payback", "Flash", "Swords Dance", "Dark Pulse", "X-Scissor", "Sleep Talk", "Poison Jab", "Swagger", "Substitute", "Cut", "Strength", "Rock Smash", "Aqua Tail"], "tr": []}, "stats": {"hp": {"name": "HP", "base": 40, "min": 190, "max": 284}, "attack": {"name": "Attack", "base": 50, "min": 94, "max": 218}, "defense": {"name": "Defense", "base": 90, "min": 166, "max": 306}, "spAttack": {"name": "Sp. Attack", "base": 90, "min": 166, "max": 306}, "spDefense": {"name": "Sp. Defense", "base": 90, "min": 166, "max": 306}, "speed": {"name": "Speed", "base": 40, "min": 190, "max": 284}}}