{"name": "Typhlosion", "id": "157", "imageUrl": "https://assets.pokemon.com/assets/cms2/img/pokedex/full/157.png", "types": ["Fire", "Ghost"], "info": {"description": "", "species": "Volcano Pok\u00e9mon", "height": "1.7m", "weight": "79.5kg", "catchRate": "45", "baseExp": "240", "growthRate": "Medium Slow", "eggGroups": ["Field"]}, "evolutions": ["Cyndaquil", "Quilava", "Typhlosion", "Typhlosion"], "moves": {"levelUp": ["Double-Edge", "Ember", "Eruption", "Gyro Ball", "Leer", "Smokescreen", "Tackle", "Quick Attack", "Flame Wheel", "Defense Curl", "Swift", "Flame Charge", "Lava Plume", "Flamethrower", "Inferno", "Rollout", "Burn Up", "Hex", "Infernal Parade", "Overheat", "Shadow Ball"], "egg": ["Covet", "Crush Claw", "Double-Edge", "Double Kick", "Extrasensory", "Flare Blitz", "Fury Swipes", "Howl", "Nature Power", "Quick Attack", "Reversal", "Thrash", "Blast Burn", "Aerial Ace", "Bulldoze", "Calm Mind", "Drain Punch", "Fire Punch", "Flamethrower", "Giga Impact", "Hyper Beam", "Iron Tail", "Mystical Fire", "Ominous Wind", "Rest", "Rock Slide", "Rock Smash", "Shadow Ball", "Shadow Claw", "Swift", "Thunder Punch", "Wild Charge"], "tutor": ["Blast Burn"], "tm": ["Focus Punch", "Roar", "Work Up", "Sunny Day", "Hyper Beam", "Protect", "Solar Beam", "Earthquake", "Dig", "Brick Break", "Double Team", "Flamethrower", "Fire Blast", "Rock Tomb", "Aerial Ace", "Facade", "Rest", "Attract", "Overheat", "Focus Blast", "Fling", "Endure", "Will-O-Wisp", "Shadow Claw", "Giga Impact", "Gyro Ball", "Rock Slide", "Sleep Talk", "Bulldoze", "Swagger", "Substitute", "Cut", "Strength", "Rock Smash", "Rock Climb"], "tr": []}, "stats": {"hp": {"name": "HP", "base": 78, "min": 266, "max": 360}, "attack": {"name": "Attack", "base": 84, "min": 155, "max": 293}, "defense": {"name": "Defense", "base": 78, "min": 144, "max": 280}, "spAttack": {"name": "Sp. Attack", "base": 78, "min": 144, "max": 280}, "spDefense": {"name": "Sp. Defense", "base": 78, "min": 144, "max": 280}, "speed": {"name": "Speed", "base": 78, "min": 266, "max": 360}}}